vote_extractor/__main__.py
vote_extractor/args.py
vote_extractor/extraction.py
vote_extractor-0.1.3.dist-info/METADATA
vote_extractor-0.1.3.dist-info/WHEEL
vote_extractor-0.1.3.dist-info/entry_points.txt
vote_extractor-0.1.3.dist-info/RECORD
