Metadata-Version: 2.1
Name: vote-extractor
Version: 0.1.3
Summary: Simple python cli to extract voting results from PDfs published by the swiss parliament.
Author: olivier
Author-email: olibitter@gmail.com
Requires-Python: >=3.10,<4.0
Classifier: Programming Language :: Python :: 3
Classifier: Programming Language :: Python :: 3.10
Classifier: Programming Language :: Python :: 3.11
Classifier: Programming Language :: Python :: 3.12
Requires-Dist: argparse (>=1.4.0,<2.0.0)
Requires-Dist: camelot-py (>=0.11.0,<0.12.0)
Requires-Dist: ghostscript (>=0.7,<0.8)
Requires-Dist: opencv-python (>=4.7.0.72,<5.0.0.0)
Requires-Dist: requests (>=2.31.0,<3.0.0)
